openedx_owly_apis/__init__.py
openedx_owly_apis/apps.py
openedx_owly_apis/models.py
openedx_owly_apis/permissions.py
openedx_owly_apis/urls.py
openedx_owly_apis/operations/__init__.py
openedx_owly_apis/operations/analytics.py
openedx_owly_apis/operations/config.py
openedx_owly_apis/operations/courses.py
openedx_owly_apis/settings/__init__.py
openedx_owly_apis/settings/common.py
openedx_owly_apis/templates/openedx_owly_apis/base.html
openedx_owly_apis/utils/__init__.py
openedx_owly_apis/utils/base_views.py
openedx_owly_apis/views/__init__.py
openedx_owly_apis/views/v1/__init__.py
openedx_owly_apis/views/v1/analytics.py
openedx_owly_apis/views/v1/config_openedx.py
openedx_owly_apis/views/v1/courses.py
openedx_owly_apis/views/v1/roles.py
openedx_owly_apis/views/v2/__init__.py
openedx_owly_apis/views/v2/exceptions.py
openedx_owly_apis/views/v2/serializers.py
openedx_owly_apis/views/v2/swagger_schemas.py
openedx_owly_apis/views/v2/urls.py
openedx_owly_apis/views/v2/validators.py
openedx_owly_apis/views/v2/views.py
openedx_owly_apis-1.6.3.dist-info/licenses/LICENSE.txt
openedx_owly_apis-1.6.3.dist-info/METADATA
openedx_owly_apis-1.6.3.dist-info/WHEEL
openedx_owly_apis-1.6.3.dist-info/entry_points.txt
openedx_owly_apis-1.6.3.dist-info/top_level.txt
openedx_owly_apis-1.6.3.dist-info/RECORD
