Metadata-Version: 2.4
Name: openedx-owly-apis
Version: 1.6.3
Summary: One-line description for README and other doc files.
Home-page: https://github.com/aulasneo/openedx-owly-apis
Author: lberoes@aulasneo.com
Author-email: lberoes@aulasneo.com
License: AGPL 3.0
Keywords: Python edx
Classifier: Development Status :: 3 - Alpha
Classifier: Framework :: Django
Classifier: Framework :: Django :: 4.2
Classifier: Framework :: Django :: 5.2
Classifier: Intended Audience :: Developers
Classifier: License :: OSI Approved :: GNU Affero General Public License v3 or later (AGPLv3+)
Classifier: Natural Language :: English
Classifier: Programming Language :: Python :: 3
Classifier: Programming Language :: Python :: 3.12
Requires-Python: >=3.11
License-File: LICENSE.txt
Requires-Dist: Django
Requires-Dist: django-filter
Requires-Dist: djangorestframework
Requires-Dist: drf-yasg
Requires-Dist: openedx-atlas
Dynamic: author
Dynamic: author-email
Dynamic: classifier
Dynamic: description
Dynamic: description-content-type
Dynamic: home-page
Dynamic: keywords
Dynamic: license
Dynamic: license-file
Dynamic: requires-dist
Dynamic: requires-python
Dynamic: summary
